LICENSE
README.md
pyproject.toml
setup.py
RXN4Chemistry.egg-info/PKG-INFO
RXN4Chemistry.egg-info/SOURCES.txt
RXN4Chemistry.egg-info/dependency_links.txt
RXN4Chemistry.egg-info/requires.txt
RXN4Chemistry.egg-info/top_level.txt
rxn4chemistry/__init__.py
rxn4chemistry/callbacks.py
rxn4chemistry/core.py
rxn4chemistry/decorators.py
rxn4chemistry/response_handler.py
rxn4chemistry/urls.py
rxn4chemistry/utilities.py