Metadata-Version: 2.1
Name: RXN4Chemistry
Version: 1.14.0
Summary: Python wrapper for IBM RXN for Chemistry
Home-page: https://github.com/rxn4chemistry/rxn4chemistry
Author: RXN for Chemistry team
Author-email: phs@zurich.ibm.com, tte@zurich.ibm.com, obc@zurich.ibm.com, ava@zurich.ibm.com, dpr@zurich.ibm.com
License: MIT
Platform: UNKNOWN
Classifier: Intended Audience :: Developers
Classifier: Intended Audience :: Science/Research
Classifier: License :: OSI Approved :: MIT License
Classifier: Programming Language :: Python :: 3.6
Classifier: Programming Language :: Python :: 3.7
Classifier: Topic :: Software Development :: Libraries :: Python Modules
License-File: LICENSE
